kxmcmfsw/__init__.py
kxmcmfsw/file_operation.py
kxmcmfsw-0.1.3.dist-info/METADATA
kxmcmfsw-0.1.3.dist-info/WHEEL
kxmcmfsw-0.1.3.dist-info/entry_points.txt
kxmcmfsw-0.1.3.dist-info/RECORD
